qdsl/__init__.py
qdsl/__main__.py
qdsl/boolean.py
qdsl/cli.py
qdsl/queryable.py
qdsl/tree.py
qdsl-0.2.4.dist-info/LICENSE
qdsl-0.2.4.dist-info/METADATA
qdsl-0.2.4.dist-info/WHEEL
qdsl-0.2.4.dist-info/entry_points.txt
qdsl-0.2.4.dist-info/top_level.txt
qdsl-0.2.4.dist-info/RECORD
