Metadata-Version: 2.1
Name: qdsl
Version: 0.2.4
Summary: qdsl takes the tedium out of nested dicts and lists.
Home-page: https://github.com/csams/qdsl
Author: Christopher Sams
Author-email: cwsams@gmail.com
License: Apache 2.0
Platform: UNKNOWN
Classifier: Development Status :: 3 - Alpha
Classifier: Intended Audience :: Developers
Classifier: Natural Language :: English
Classifier: License :: OSI Approved :: Apache Software License
Classifier: Programming Language :: Python
Classifier: Programming Language :: Python :: 2.7
Classifier: Programming Language :: Python :: 3.6
Classifier: Programming Language :: Python :: 3.7
Classifier: Programming Language :: Python :: 3.8
Requires-Dist: pyyaml
Requires-Dist: IPython
Requires-Dist: requests
Requires-Dist: pandas
Provides-Extra: develop
Requires-Dist: sphinx-rtd-theme ; extra == 'develop'
Requires-Dist: twine ; extra == 'develop'
Requires-Dist: wheel ; extra == 'develop'
Requires-Dist: pytest-cov ; extra == 'develop'
Requires-Dist: flake8 ; extra == 'develop'
Requires-Dist: pytest ; extra == 'develop'
Requires-Dist: coverage ; extra == 'develop'
Requires-Dist: setuptools ; extra == 'develop'
Requires-Dist: Sphinx ; extra == 'develop'
